{"title":"Combined feed","url":"https://MOVIECORD.github.io/recruit/all.xml","elements":[{"title":"상업적인 시나리오 개발을 위한 스터디 팀원 모집 (아이템 개발, 공모전 준비 등) (씨네21 ─ 영화인 리쿠르트)","contents":"<b>\n\t\t\t\tSAT 개발팀\t\t\t</b>","link":"http://b.cine21.com/bbs/board.php?bo_table=recruit&wr_id=19913","retrieved":1706938627762},{"title":"영화사 홀리가든에서 2024년 상반기 신입/경력사원을 모집합니다. (씨네21 ─ 영화인 리쿠르트)","contents":"<b>\n\t\t\t\t홀리가든\t\t\t</b>","link":"http://b.cine21.com/bbs/board.php?bo_table=recruit&wr_id=19912","retrieved":1706895433107},{"title":"[무주산골영화제] 제12회 무주산골영화제 사무국 스태프 3차 채용 공고 (씨네21 ─ 영화인 리쿠르트)","contents":"<b>\n\t\t\t\t(재)무주산골문화재단\t\t\t</b>","link":"http://b.cine21.com/bbs/board.php?bo_table=recruit&wr_id=19911","retrieved":1706895433107},{"title":"제12회 서울국제어린이영화제 1차 스태프 모집 (씨네21 ─ 영화인 리쿠르트)","contents":"<b>\n\t\t\t\t서울국제어린이영화제\t\t\t</b>","link":"http://b.cine21.com/bbs/board.php?bo_table=recruit&wr_id=19910","retrieved":1706895433108},{"title":"[공고] 씨네큐브 발권업무 아르바이트 모집 (씨네21 ─ 영화인 리쿠르트)","contents":"<b>\n\t\t\t\t씨네큐브\t\t\t</b>","link":"http://b.cine21.com/bbs/board.php?bo_table=recruit&wr_id=19909","retrieved":1706809046534},{"title":"[충무로영상센터 오!재미동] 2024 독립영화촬영지원사업 '시작이오' 안내 (씨네21 ─ 영화인 리쿠르트)","contents":"<b>\n\t\t\t\t서울영상위원회 충무로영상센터\t\t\t</b>","link":"http://b.cine21.com/bbs/board.php?bo_table=recruit&wr_id=19908","retrieved":1706765846073},{"title":"[든든] 2월 영상산업 내 성폭력 예방교육 안내(2월 15일/2월 29일 목요일 진행) (씨네21 ─ 영화인 리쿠르트)","contents":"<b>\n\t\t\t\t한국영화성평등센터 든든\t\t\t</b>","link":"http://b.cine21.com/bbs/board.php?bo_table=recruit&wr_id=19907","retrieved":1706765846075},{"title":"[채용] 플러스엠 엔터테인먼트 콘텐트담당 '인턴' 모집 (~02/12 서류 마감) (씨네21 ─ 영화인 리쿠르트)","contents":"<b>\n\t\t\t\t플러스엠 엔터테인먼트\t\t\t</b>","link":"http://b.cine21.com/bbs/board.php?bo_table=recruit&wr_id=19906","retrieved":1706722625336},{"title":"'고전 영화 읽고 글쓰기 클럽' 멤버를 모집합니다.(2월 영화: 압바스 키아로스타미 <체리향기>) (씨네21 ─ 영화인 리쿠르트)","contents":"<b>\n\t\t\t\t키노캔버스\t\t\t</b>","link":"http://b.cine21.com/bbs/board.php?bo_table=recruit&wr_id=19905","retrieved":1706722625337},{"title":"'삶을 위한 영화 에세이 쓰기 클럽' 멤버를 모집합니다.(2월 영화: <칠드런 액트>) (씨네21 ─ 영화인 리쿠르트)","contents":"<b>\n\t\t\t\t키노캔버스\t\t\t</b>","link":"http://b.cine21.com/bbs/board.php?bo_table=recruit&wr_id=19904","retrieved":1706722625337},{"title":"경기 스토리작가 창작소 고양 5기·파주 6기 참여작가 모집 (씨네21 ─ 영화인 리쿠르트)","contents":"<b>\n\t\t\t\t한국영화프로듀서조합\t\t\t</b>","link":"http://b.cine21.com/bbs/board.php?bo_table=recruit&wr_id=19903","retrieved":1706636222164},{"title":"[모호필름] 기획마케팅팀 신입직원 모집\t\t\t\t\t\t\t\t\t댓글+1개 (씨네21 ─ 영화인 리쿠르트)","contents":"<b>\n\t\t\t\t모호필름\t\t\t</b>","link":"http://b.cine21.com/bbs/board.php?bo_table=recruit&wr_id=19899","retrieved":1706636222166},{"title":"[영화장르분석모임] 멤버 모집 (씨네21 ─ 영화인 리쿠르트)","contents":"<b>\n\t\t\t\t세미나\t\t\t</b>","link":"http://b.cine21.com/bbs/board.php?bo_table=recruit&wr_id=19896","retrieved":1706549826040},{"title":"2024년 영화 디지털 마케팅 신입 채용 [절찬상영중] (씨네21 ─ 영화인 리쿠르트)","contents":"<b>\n\t\t\t\t절찬상영중\t\t\t</b>","link":"http://b.cine21.com/bbs/board.php?bo_table=recruit&wr_id=19892","retrieved":1706549826042},{"title":"NCH 현지화 프로젝트 매니저(PM) (씨네21 ─ 영화인 리쿠르트)","contents":"<b>\n\t\t\t\t넥서스\t\t\t</b>","link":"http://b.cine21.com/bbs/board.php?bo_table=recruit&wr_id=19891","retrieved":1706506659797}]}