{"title":"Combined feed","url":"https://MOVIECORD.github.io/recruit/all.xml","elements":[{"title":"(주)넥서스 미디어 회사 국내마케팅팀 프로젝트 매니저 모십니다 (씨네21 ─ 영화인 리쿠르트)","contents":"<b>\n\t\t\t\t(주)넥서스\t\t\t</b>","link":"http://b.cine21.com/bbs/board.php?bo_table=recruit&wr_id=17520","retrieved":1644341989789},{"title":"[더틱톡] 드라마/예능 홍보대행 2022년 신입 공고 (씨네21 ─ 영화인 리쿠르트)","contents":"<b>\n\t\t\t\t더틱톡\t\t\t</b>","link":"http://b.cine21.com/bbs/board.php?bo_table=recruit&wr_id=17519","retrieved":1644341989794},{"title":"제23회 전주국제영화제 단기스태프 모집 (씨네21 ─ 영화인 리쿠르트)","contents":"<b>\n\t\t\t\t전주국제영화제조직위원회\t\t\t</b>","link":"http://b.cine21.com/bbs/board.php?bo_table=recruit&wr_id=17518","retrieved":1644341989794},{"title":"제26회 BIFAN, NAFF 워크 인 프로그레스 공모 (~2월 15일) (씨네21 ─ 영화인 리쿠르트)","contents":"<b>\n\t\t\t\t부천국제판타스틱영화제\t\t\t</b>","link":"http://b.cine21.com/bbs/board.php?bo_table=recruit&wr_id=17517","retrieved":1644255535506},{"title":"출판도시문화재단 영화문화진흥사업 프로젝트 매니저 채용 공고 (씨네21 ─ 영화인 리쿠르트)","contents":"<b>\n\t\t\t\t출판도시문화재단\t\t\t</b>","link":"http://b.cine21.com/bbs/board.php?bo_table=recruit&wr_id=17516","retrieved":1644255535506},{"title":"[무주산골영화제] 제10회 무주산골영화제 2차 사무국 스태프 채용공고 (씨네21 ─ 영화인 리쿠르트)","contents":"<b>\n\t\t\t\t무주산골영화제\t\t\t</b>","link":"http://b.cine21.com/bbs/board.php?bo_table=recruit&wr_id=17515","retrieved":1644255535507},{"title":"[KSI] 기초반 12기 수강생 모집 공고 (얼리버드 할인 이벤트 진행 중, 02/17일 마감) (씨네21 ─ 영화인 리쿠르트)","contents":"<b>\n\t\t\t\t한국시나리오연구소\t\t\t</b>","link":"http://b.cine21.com/bbs/board.php?bo_table=recruit&wr_id=17514","retrieved":1644255535508},{"title":"[로카] 영화사 취업 설명회 by LOCA in 건대입구 예매 오픈! (씨네21 ─ 영화인 리쿠르트)","contents":"<b>\n\t\t\t\t아카데미 로카\t\t\t</b>","link":"http://b.cine21.com/bbs/board.php?bo_table=recruit&wr_id=17513","retrieved":1644212244601},{"title":"[공모] 2022년 상반기 <제21회 필름게이트> 공모(~3.20) (씨네21 ─ 영화인 리쿠르트)","contents":"<b>\n\t\t\t\t신영균예술문화재단\t\t\t</b>","link":"http://b.cine21.com/bbs/board.php?bo_table=recruit&wr_id=17512","retrieved":1644212244601},{"title":"[로카] <영화 비즈니스 취업 준비 과정 27기> & <영화 비즈니스 입문 49기> 수강생 모집 (씨네21 ─ 영화인 리쿠르트)","contents":"<b>\n\t\t\t\t아카데미 로카\t\t\t</b>","link":"http://b.cine21.com/bbs/board.php?bo_table=recruit&wr_id=17511","retrieved":1644212244623},{"title":"주식회사 절찬상영중 2022 신입, 경력 모집 (씨네21 ─ 영화인 리쿠르트)","contents":"<b>\n\t\t\t\t절찬상영중\t\t\t</b>","link":"http://b.cine21.com/bbs/board.php?bo_table=recruit&wr_id=17510","retrieved":1644212244623},{"title":"서울환경영화제 홍보팀장 상근자채용 (~2/8) (씨네21 ─ 영화인 리쿠르트)","contents":"<b>\n\t\t\t\t환경재단\t\t\t</b>","link":"http://b.cine21.com/bbs/board.php?bo_table=recruit&wr_id=17509","retrieved":1643996245114},{"title":"(주)영화인 홍보마케팅 담당 경력 사원 채용 공고 (씨네21 ─ 영화인 리쿠르트)","contents":"<b>\n\t\t\t\t주식회사 영화인\t\t\t</b>","link":"http://b.cine21.com/bbs/board.php?bo_table=recruit&wr_id=17508","retrieved":1643953038897},{"title":"크리픽쳐스 신입사원 및 경력직 기획 PD 채용 공고 (씨네21 ─ 영화인 리쿠르트)","contents":"<b>\n\t\t\t\t크리픽쳐스\t\t\t</b>","link":"http://b.cine21.com/bbs/board.php?bo_table=recruit&wr_id=17507","retrieved":1643910022590},{"title":"[키노라이츠] 상상마당 시네마 홍대 현장 스태프 채용 공고 (씨네21 ─ 영화인 리쿠르트)","contents":"<b>\n\t\t\t\t키노라이츠\t\t\t</b>","link":"http://b.cine21.com/bbs/board.php?bo_table=recruit&wr_id=17506","retrieved":1643910022590}]}