{"title":"씨네21 ─ 영화인 리쿠르트","url":"http://b.cine21.com/bbs/board.php?bo_table=recruit","favicon":"http://b.cine21.com/bbs/favicon.ico","elements":[{"title":"[김포국제청소년영화제] 넷플릭스 흥행작 'D.P' 한준희 감독 초청 마스터 클래스 개최","contents":"<b>\n\t\t\t\t김포국제청소년영화제\t\t\t</b>","link":"http://b.cine21.com/bbs/board.php?bo_table=recruit&wr_id=17252","retrieved":1635874899410},{"title":"강좌_영화 비즈니스 입문","contents":"<b>\n\t\t\t\t아카데미 로카\t\t\t</b>","link":"http://b.cine21.com/bbs/board.php?bo_table=recruit&wr_id=17251","retrieved":1635874899411},{"title":"영화사 직원(외화수입및 배급업무) 및 스토리 작가와/그림작가(웹툰 및)를 구합니다\t\t\t\t\t\t\t\t\t댓글+2개","contents":"<b>\n\t\t\t\t미디어마그나\t\t\t</b>","link":"http://b.cine21.com/bbs/board.php?bo_table=recruit&wr_id=17248","retrieved":1635874899412},{"title":"[왓챠] 광고영업 담당자 모집","contents":"<b>\n\t\t\t\t왓챠\t\t\t</b>","link":"http://b.cine21.com/bbs/board.php?bo_table=recruit&wr_id=17247","retrieved":1635831131867},{"title":"[왓챠] 오리지널 콘텐츠 해외 세일즈 매니저 모집","contents":"<b>\n\t\t\t\t왓챠\t\t\t</b>","link":"http://b.cine21.com/bbs/board.php?bo_table=recruit&wr_id=17246","retrieved":1635831131868},{"title":"제4회 무중력영화제 리플레이 상영회 신청 (11/18-20 @CGV목동)","contents":"<b>\n\t\t\t\t무중력지대 양천\t\t\t</b>","link":"http://b.cine21.com/bbs/board.php?bo_table=recruit&wr_id=17245","retrieved":1635788518837},{"title":"제4회 무중력영화제 리플레이 상영회 신청 (11/18-20 @CGV목동)","contents":"<b>\n\t\t\t\t무중력지대 양천\t\t\t</b>","link":"http://b.cine21.com/bbs/board.php?bo_table=recruit&wr_id=17244","retrieved":1635788518838},{"title":"[MBC아카데미] ‘영화홍보마케팅&프로듀서’ 2022 상반기 실무멘토링 과정 모집!","contents":"<b>\n\t\t\t\tMBC아카데미 문화연출학부\t\t\t</b>","link":"http://b.cine21.com/bbs/board.php?bo_table=recruit&wr_id=17243","retrieved":1635788518840},{"title":"제23회 전주국제영화제 스태프 모집(1차)","contents":"<b>\n\t\t\t\t전주국제영화제조직위원회\t\t\t</b>","link":"http://b.cine21.com/bbs/board.php?bo_table=recruit&wr_id=17240","retrieved":1635788518841},{"title":"제18회 서울국제사랑영화제 개최 안내 (온라인 무료상영)","contents":"<b>\n\t\t\t\t서울국제사랑영화제\t\t\t</b>","link":"http://b.cine21.com/bbs/board.php?bo_table=recruit&wr_id=17239","retrieved":1635744767324},{"title":"프로젝트 매니저 (정규직) 채용","contents":"<b>\n\t\t\t\t비스포크랩 주식회사\t\t\t</b>","link":"http://b.cine21.com/bbs/board.php?bo_table=recruit&wr_id=17238","retrieved":1635600876379},{"title":"한영 또는 영한 자막 감수자 채용 (정규직)","contents":"<b>\n\t\t\t\t비스포크랩 주식회사\t\t\t</b>","link":"http://b.cine21.com/bbs/board.php?bo_table=recruit&wr_id=17237","retrieved":1635600876381},{"title":"한영/영한/중한/일한 자막 번역가, 영한 더빙 번역가, 타임코더, 캡션 제작자 모집 (프리랜서)","contents":"<b>\n\t\t\t\t비스포크랩 주식회사\t\t\t</b>","link":"http://b.cine21.com/bbs/board.php?bo_table=recruit&wr_id=17236","retrieved":1635600876382},{"title":"[든든] 11월 영화계 성희롱 예방교육 안내(11월 10일 / 11월 24일 개최)","contents":"<b>\n\t\t\t\t한국영화성평등센터 든든\t\t\t</b>","link":"http://b.cine21.com/bbs/board.php?bo_table=recruit&wr_id=17235","retrieved":1635600876384},{"title":"스튜디오앤뉴 영화사업부 제작관리 경력 모집","contents":"<b>\n\t\t\t\t스튜디오앤뉴\t\t\t</b>","link":"http://b.cine21.com/bbs/board.php?bo_table=recruit&wr_id=17234","retrieved":1635600876385}]}